MANIFEST.in
README.md
pyproject.toml
setup.py
Lido_vsmelov.egg-info/PKG-INFO
Lido_vsmelov.egg-info/SOURCES.txt
Lido_vsmelov.egg-info/dependency_links.txt
Lido_vsmelov.egg-info/requires.txt
Lido_vsmelov.egg-info/top_level.txt
lido/__init__.py
lido/beacon.py
lido/fetch_and_validate.py
lido/find_duplicates.py
lido/get_operators_data.py
lido/get_operators_keys.py
lido/get_stats.py
lido/validate_keys.py
lido/constants/chains.py
lido/constants/contract_addresses.py
lido/contracts/abi_loader.py
lido/contracts/w3_contracts.py
lido/contracts/abi/goerli/Lido.json
lido/contracts/abi/goerli/NodeOperatorsRegistry.json
lido/contracts/abi/mainnet/Lido.json
lido/contracts/abi/mainnet/NodeOperatorsRegistry.json
lido/eth2deposit/settings.py
lido/eth2deposit/utils/constants.py
lido/eth2deposit/utils/ssz.py
lido/multicall/__init__.py
lido/multicall/call.py
lido/multicall/constants.py
lido/multicall/multicall.py
lido/multicall/signature.py
lido/utils/data_actuality.py
venv/bin/rst2html.py
venv/bin/rst2html4.py
venv/bin/rst2html5.py
venv/bin/rst2latex.py
venv/bin/rst2man.py
venv/bin/rst2odt.py
venv/bin/rst2odt_prepstyles.py
venv/bin/rst2pseudoxml.py
venv/bin/rst2s5.py
venv/bin/rst2xetex.py
venv/bin/rst2xml.py
venv/bin/rstpep2html.py