Metadata-Version: 2.1
Name: Lido-vsmelov
Version: 0.2.1
Summary: Network helpers for Lido
Home-page: https://github.com/lidofinance/lido-python
Author: Lido
Author-email: info@lido.fi
License: MIT
Platform: UNKNOWN
Requires-Python: >=3.0,<4
